{
  "week": "11-15 августа 2025",
  "menu": {
    "Понедельник": [
      "Картофельное пюре с котлетой из свинины в томатном соусе",
      "Салат из огурцов и помидоров"
    ],
    "Вторник": [
      "Гречка с грибным соусом и рубленая куриная котлета",
      "Салат из свеклы с чесноком и майонезом"
    ],
    "Среда": [
      "Плов из свинины",
      "Салат из огурцов и капусты"
    ],
    "Четверг": [
      "Спагетти с фаршем в томатном соусе",
      "Салат морковь с майонезом и чесноком"
    ],
    "Пятница": [
      "Гречка с куриной котлетой в томатно-сливочном соусе",
      "Салат из огурцов и помидоров"
    ]
  }
}